crypto_pt/__init__.py
crypto_pt/core.py
crypto_pt-0.1.0.dist-info/licenses/LICENSE.txt
crypto_pt-0.1.0.dist-info/METADATA
crypto_pt-0.1.0.dist-info/WHEEL
crypto_pt-0.1.0.dist-info/top_level.txt
crypto_pt-0.1.0.dist-info/RECORD
