Metadata-Version: 2.4
Name: crypto-pt
Version: 0.1.0
Summary: Uma biblioteca Python para criptografia e descriptografia RSA em português.
Home-page: https://github.com/kikkask/crypto-pt
Author: Lucas Cordeiro
Author-email: sirbritolucas@gmail.com
Project-URL: Bug Reports, https://github.com/kikkask/crypto-pt/issues
Project-URL: Source, https://github.com/kikkask/crypto-pt/
Keywords: rsa,cryptography,encryption,decryption,crypto,pt,portugues
Classifier: Development Status :: 3 - Alpha
Classifier: Intended Audience :: Developers
Classifier: Topic :: Security :: Cryptography
Classifier: License :: OSI Approved :: MIT License
Classifier: Programming Language :: Python :: 3
Classifier: Programming Language :: Python :: 3.7
Classifier: Programming Language :: Python :: 3.8
Classifier: Programming Language :: Python :: 3.9
Classifier: Programming Language :: Python :: 3.10
Classifier: Programming Language :: Python :: 3.11
Classifier: Operating System :: OS Independent
Requires-Python: >=3.7
License-File: LICENSE.txt
Dynamic: author
Dynamic: author-email
Dynamic: classifier
Dynamic: description
Dynamic: description-content-type
Dynamic: home-page
Dynamic: keywords
Dynamic: license-file
Dynamic: project-url
Dynamic: requires-python
Dynamic: summary
